CHANGES.txt
MANIFEST.in
README.md
README.txt
setup.py
worker.ini
ztq_worker/__init__.py
ztq_worker/buffer_thread.py
ztq_worker/command_execute.py
ztq_worker/command_thread.py
ztq_worker/config_manager.py
ztq_worker/job_thread.py
ztq_worker/job_thread_manager.py
ztq_worker/main.py
ztq_worker.egg-info/PKG-INFO
ztq_worker.egg-info/SOURCES.txt
ztq_worker.egg-info/dependency_links.txt
ztq_worker.egg-info/entry_points.txt
ztq_worker.egg-info/not-zip-safe
ztq_worker.egg-info/requires.txt
ztq_worker.egg-info/top_level.txt
ztq_worker/system_info/README.txt
ztq_worker/system_info/__init__.py
ztq_worker/system_info/__init__.pyc
ztq_worker/system_info/get_cpu_style.vbs
ztq_worker/system_info/get_cpu_usage.vbs
ztq_worker/system_info/get_mem_usage.vbs
ztq_worker/system_info/linux.py
ztq_worker/system_info/linux.pyc
ztq_worker/system_info/win.py