Metadata-Version: 1.1
Name: ztq-worker
Version: 1.2.3
Summary: Zopen Task Queue Worker
Home-page: UNKNOWN
Author: xutaozhe
Author-email: xutaozhe@zopen.cn
License: MIT
Keywords: Everydo queue async ztq_worker
Platform: UNKNOWN
Classifier: Development Status :: 4 - Beta
Classifier: Environment :: Web Environment
Classifier: Intended Audience :: Developers
Classifier: Programming Language :: Python
Classifier: Operating System :: OS Independent
Classifier: Topic :: Internet :: WWW/HTTP
